phox_modbus/__init__.py
phox_modbus/modbus.py
phox_modbus-1.2.2.dist-info/METADATA
phox_modbus-1.2.2.dist-info/WHEEL
phox_modbus-1.2.2.dist-info/licenses/LICENSE
phox_modbus-1.2.2.dist-info/RECORD
