Metadata-Version: 2.4
Name: phox-modbus
Version: 1.2.2
Summary: Basic drivers to manage PHOXENE flash devices
Project-URL: Homepage, https://www.phoxene.com
Author-email: Aurelien PLANTIN <a.plantin@phoxene.com>
License-Expression: MIT
License-File: LICENSE
Keywords: Sx-IP,Sx-LED,SxIP,phoxene,python
Classifier: Intended Audience :: Developers
Classifier: License :: OSI Approved :: MIT License
Classifier: Operating System :: OS Independent
Classifier: Programming Language :: Python :: 3.7
Classifier: Programming Language :: Python :: 3.8
Classifier: Programming Language :: Python :: 3.9
Classifier: Programming Language :: Python :: 3.10
Classifier: Programming Language :: Python :: 3.11
Classifier: Programming Language :: Python :: 3.12
Requires-Python: >=3.7
Requires-Dist: pyserial>=3.5
Provides-Extra: dev
Requires-Dist: build; extra == 'dev'
Requires-Dist: sphinx; extra == 'dev'
Requires-Dist: sphinx-rtd-theme; extra == 'dev'
Requires-Dist: twine; extra == 'dev'
Requires-Dist: unittest; extra == 'dev'
Provides-Extra: docs
Requires-Dist: myst-parser; extra == 'docs'
Requires-Dist: sphinx-autodoc-typehints; extra == 'docs'
Requires-Dist: sphinx-rtd-theme; extra == 'docs'
Requires-Dist: sphinx>=7.0; extra == 'docs'
